[{"name":"Product 1","price":120,"finalPrice":105.6,"brand":"Nintendo","genre":"Adventures","src":"https://via.placeholder.com/150x200"},{"name":"Product 2","price":240,"finalPrice":211.2,"brand":"Xbox","genre":"Shooter","src":"https://via.placeholder.com/150x200"},{"name":"Product 3","price":360,"finalPrice":316.8,"brand":"Sony","genre":"Adventures","src":"https://via.placeholder.com/150x200"},{"name":"Product 4","price":480,"finalPrice":422.4,"brand":"Sony","genre":"Racing","src":"https://via.placeholder.com/150x200"},{"name":"Product 5","price":600,"finalPrice":528,"brand":"Xbox","genre":"Adventures","src":"https://via.placeholder.com/150x200"},{"name":"Product 6","price":720,"finalPrice":633.6,"brand":"Sony","genre":"Racing","src":"https://via.placeholder.com/150x200"},{"name":"Product 7","price":840,"finalPrice":739.2,"brand":"Sony","genre":"Shooter","src":"https://via.placeholder.com/150x200"},{"name":"Product 8","price":960,"finalPrice":844.8,"brand":"Sony","genre":"Shooter","src":"https://via.placeholder.com/150x200"},{"name":"Product 9","price":1080,"finalPrice":950.4,"brand":"Sony","genre":"Party","src":"https://via.placeholder.com/150x200"},{"name":"Product 10","price":1200,"finalPrice":1056,"brand":"Xbox","genre":"Sports","src":"https://via.placeholder.com/150x200"},{"name":"Product 11","price":1320,"finalPrice":1161.6,"brand":"Sony","genre":"Fighting","src":"https://via.placeholder.com/150x200"},{"name":"Product 12","price":1440,"finalPrice":1267.2,"brand":"Sony","genre":"Adventures","src":"https://via.placeholder.com/150x200"},{"name":"Product 13","price":1560,"finalPrice":1372.8,"brand":"Sony","genre":"Racing","src":"https://via.placeholder.com/150x200"},{"name":"Product 14","price":1680,"finalPrice":1478.4,"brand":"Xbox","genre":"Adventures","src":"https://via.placeholder.com/150x200"},{"name":"Product 15","price":1800,"finalPrice":1584,"brand":"Sony","genre":"Party","src":"https://via.placeholder.com/150x200"},{"name":"Product 16","price":1920,"finalPrice":1689.6,"brand":"Xbox","genre":"Party","src":"https://via.placeholder.com/150x200"},{"name":"Product 17","price":2040,"finalPrice":1795.2,"brand":"Nintendo","genre":"Fighting","src":"https://via.placeholder.com/150x200"},{"name":"Product 18","price":2160,"finalPrice":1900.8,"brand":"Sony","genre":"Shooter","src":"https://via.placeholder.com/150x200"},{"name":"Product 19","price":2280,"finalPrice":2006.4,"brand":"Nintendo","genre":"Fighting","src":"https://via.placeholder.com/150x200"},{"name":"Product 20","price":2400,"finalPrice":2112,"brand":"Sony","genre":"Party","src":"https://via.placeholder.com/150x200"},{"name":"Product 21","price":2520,"finalPrice":2217.6,"brand":"Xbox","genre":"Adventures","src":"https://via.placeholder.com/150x200"},{"name":"Product 22","price":2640,"finalPrice":2323.2,"brand":"Sony","genre":"Sports","src":"https://via.placeholder.com/150x200"},{"name":"Product 23","price":2760,"finalPrice":2428.8,"brand":"Sony","genre":"Fighting","src":"https://via.placeholder.com/150x200"},{"name":"Product 24","price":2880,"finalPrice":2534.4,"brand":"Sony","genre":"Fighting","src":"https://via.placeholder.com/150x200"},{"name":"Product 25","price":3000,"finalPrice":2640,"brand":"Nintendo","genre":"Shooter","src":"https://via.placeholder.com/150x200"},{"name":"Product 26","price":3120,"finalPrice":2745.6,"brand":"Nintendo","genre":"Sports","src":"https://via.placeholder.com/150x200"},{"name":"Product 27","price":3240,"finalPrice":2851.2,"brand":"Sony","genre":"Party","src":"https://via.placeholder.com/150x200"},{"name":"Product 28","price":3360,"finalPrice":2956.8,"brand":"Sony","genre":"Adventures","src":"https://via.placeholder.com/150x200"},{"name":"Product 29","price":3480,"finalPrice":3062.4,"brand":"Xbox","genre":"Racing","src":"https://via.placeholder.com/150x200"},{"name":"Product 30","price":3600,"finalPrice":3168,"brand":"Xbox","genre":"Sports","src":"https://via.placeholder.com/150x200"},{"name":"Product 31","price":3720,"finalPrice":3273.6,"brand":"Xbox","genre":"Party","src":"https://via.placeholder.com/150x200"},{"name":"Product 32","price":3840,"finalPrice":3379.2,"brand":"Nintendo","genre":"Shooter","src":"https://via.placeholder.com/150x200"},{"name":"Product 33","price":3960,"finalPrice":3484.8,"brand":"Nintendo","genre":"Adventures","src":"https://via.placeholder.com/150x200"},{"name":"Product 34","price":4080,"finalPrice":3590.4,"brand":"Xbox","genre":"Adventures","src":"https://via.placeholder.com/150x200"},{"name":"Product 35","price":4200,"finalPrice":3696,"brand":"Nintendo","genre":"Adventures","src":"https://via.placeholder.com/150x200"},{"name":"Product 36","price":4320,"finalPrice":3801.6,"brand":"Xbox","genre":"Party","src":"https://via.placeholder.com/150x200"},{"name":"Product 37","price":4440,"finalPrice":3907.2,"brand":"Xbox","genre":"Adventures","src":"https://via.placeholder.com/150x200"},{"name":"Product 38","price":4560,"finalPrice":4012.8,"brand":"Xbox","genre":"Shooter","src":"https://via.placeholder.com/150x200"},{"name":"Product 39","price":4680,"finalPrice":4118.4,"brand":"Sony","genre":"Shooter","src":"https://via.placeholder.com/150x200"},{"name":"Product 40","price":4800,"finalPrice":4224,"brand":"Xbox","genre":"Adventures","src":"https://via.placeholder.com/150x200"},{"name":"Product 41","price":4920,"finalPrice":4329.6,"brand":"Nintendo","genre":"Party","src":"https://via.placeholder.com/150x200"},{"name":"Product 42","price":5040,"finalPrice":4435.2,"brand":"Nintendo","genre":"Party","src":"https://via.placeholder.com/150x200"},{"name":"Product 43","price":5160,"finalPrice":4540.8,"brand":"Sony","genre":"Party","src":"https://via.placeholder.com/150x200"},{"name":"Product 44","price":5280,"finalPrice":4646.4,"brand":"Xbox","genre":"Sports","src":"https://via.placeholder.com/150x200"},{"name":"Product 45","price":5400,"finalPrice":4752,"brand":"Xbox","genre":"Sports","src":"https://via.placeholder.com/150x200"},{"name":"Product 46","price":5520,"finalPrice":4857.6,"brand":"Nintendo","genre":"Fighting","src":"https://via.placeholder.com/150x200"},{"name":"Product 47","price":5640,"finalPrice":4963.2,"brand":"Nintendo","genre":"Fighting","src":"https://via.placeholder.com/150x200"},{"name":"Product 48","price":5760,"finalPrice":5068.8,"brand":"Sony","genre":"Adventures","src":"https://via.placeholder.com/150x200"},{"name":"Product 49","price":5880,"finalPrice":5174.4,"brand":"Sony","genre":"Fighting","src":"https://via.placeholder.com/150x200"},{"name":"Product 50","price":6000,"finalPrice":5280,"brand":"Sony","genre":"Adventures","src":"https://via.placeholder.com/150x200"},{"name":"Product 51","price":6120,"finalPrice":5385.6,"brand":"Xbox","genre":"Adventures","src":"https://via.placeholder.com/150x200"},{"name":"Product 52","price":6240,"finalPrice":5491.2,"brand":"Sony","genre":"Adventures","src":"https://via.placeholder.com/150x200"},{"name":"Product 53","price":6360,"finalPrice":5596.8,"brand":"Nintendo","genre":"Fighting","src":"https://via.placeholder.com/150x200"},{"name":"Product 54","price":6480,"finalPrice":5702.4,"brand":"Xbox","genre":"Sports","src":"https://via.placeholder.com/150x200"},{"name":"Product 55","price":6600,"finalPrice":5808,"brand":"Xbox","genre":"Fighting","src":"https://via.placeholder.com/150x200"},{"name":"Product 56","price":6720,"finalPrice":5913.6,"brand":"Nintendo","genre":"Adventures","src":"https://via.placeholder.com/150x200"},{"name":"Product 57","price":6840,"finalPrice":6019.2,"brand":"Xbox","genre":"Adventures","src":"https://via.placeholder.com/150x200"},{"name":"Product 58","price":6960,"finalPrice":6124.8,"brand":"Nintendo","genre":"Fighting","src":"https://via.placeholder.com/150x200"},{"name":"Product 59","price":7080,"finalPrice":6230.4,"brand":"Sony","genre":"Adventures","src":"https://via.placeholder.com/150x200"},{"name":"Product 60","price":7200,"finalPrice":6336,"brand":"Xbox","genre":"Adventures","src":"https://via.placeholder.com/150x200"},{"name":"Product 61","price":7320,"finalPrice":6441.6,"brand":"Xbox","genre":"Adventures","src":"https://via.placeholder.com/150x200"},{"name":"Product 62","price":7440,"finalPrice":6547.2,"brand":"Xbox","genre":"Sports","src":"https://via.placeholder.com/150x200"},{"name":"Product 63","price":7560,"finalPrice":6652.8,"brand":"Sony","genre":"Sports","src":"https://via.placeholder.com/150x200"},{"name":"Product 64","price":7680,"finalPrice":6758.4,"brand":"Xbox","genre":"Sports","src":"https://via.placeholder.com/150x200"},{"name":"Product 65","price":7800,"finalPrice":6864,"brand":"Sony","genre":"Adventures","src":"https://via.placeholder.com/150x200"},{"name":"Product 66","price":7920,"finalPrice":6969.6,"brand":"Nintendo","genre":"Racing","src":"https://via.placeholder.com/150x200"},{"name":"Product 67","price":8040,"finalPrice":7075.2,"brand":"Sony","genre":"Adventures","src":"https://via.placeholder.com/150x200"},{"name":"Product 68","price":8160,"finalPrice":7180.8,"brand":"Xbox","genre":"Racing","src":"https://via.placeholder.com/150x200"},{"name":"Product 69","price":8280,"finalPrice":7286.4,"brand":"Sony","genre":"Adventures","src":"https://via.placeholder.com/150x200"},{"name":"Product 70","price":8400,"finalPrice":7392,"brand":"Sony","genre":"Shooter","src":"https://via.placeholder.com/150x200"},{"name":"Product 71","price":8520,"finalPrice":7497.6,"brand":"Sony","genre":"Fighting","src":"https://via.placeholder.com/150x200"},{"name":"Product 72","price":8640,"finalPrice":7603.2,"brand":"Nintendo","genre":"Party","src":"https://via.placeholder.com/150x200"},{"name":"Product 73","price":8760,"finalPrice":7708.8,"brand":"Xbox","genre":"Adventures","src":"https://via.placeholder.com/150x200"},{"name":"Product 74","price":8880,"finalPrice":7814.4,"brand":"Sony","genre":"Adventures","src":"https://via.placeholder.com/150x200"},{"name":"Product 75","price":9000,"finalPrice":7920,"brand":"Xbox","genre":"Racing","src":"https://via.placeholder.com/150x200"},{"name":"Product 76","price":9120,"finalPrice":8025.6,"brand":"Sony","genre":"Shooter","src":"https://via.placeholder.com/150x200"},{"name":"Product 77","price":9240,"finalPrice":8131.2,"brand":"Xbox","genre":"Party","src":"https://via.placeholder.com/150x200"},{"name":"Product 78","price":9360,"finalPrice":8236.8,"brand":"Xbox","genre":"Adventures","src":"https://via.placeholder.com/150x200"},{"name":"Product 79","price":9480,"finalPrice":8342.4,"brand":"Sony","genre":"Adventures","src":"https://via.placeholder.com/150x200"},{"name":"Product 80","price":9600,"finalPrice":8448,"brand":"Nintendo","genre":"Party","src":"https://via.placeholder.com/150x200"},{"name":"Product 81","price":9720,"finalPrice":8553.6,"brand":"Xbox","genre":"Adventures","src":"https://via.placeholder.com/150x200"},{"name":"Product 82","price":9840,"finalPrice":8659.2,"brand":"Nintendo","genre":"Sports","src":"https://via.placeholder.com/150x200"},{"name":"Product 83","price":9960,"finalPrice":8764.8,"brand":"Nintendo","genre":"Party","src":"https://via.placeholder.com/150x200"},{"name":"Product 84","price":10080,"finalPrice":8870.4,"brand":"Xbox","genre":"Sports","src":"https://via.placeholder.com/150x200"},{"name":"Product 85","price":10200,"finalPrice":8976,"brand":"Xbox","genre":"Racing","src":"https://via.placeholder.com/150x200"},{"name":"Product 86","price":10320,"finalPrice":9081.6,"brand":"Xbox","genre":"Sports","src":"https://via.placeholder.com/150x200"},{"name":"Product 87","price":10440,"finalPrice":9187.2,"brand":"Xbox","genre":"Adventures","src":"https://via.placeholder.com/150x200"},{"name":"Product 88","price":10560,"finalPrice":9292.8,"brand":"Nintendo","genre":"Sports","src":"https://via.placeholder.com/150x200"},{"name":"Product 89","price":10680,"finalPrice":9398.4,"brand":"Xbox","genre":"Shooter","src":"https://via.placeholder.com/150x200"},{"name":"Product 90","price":10800,"finalPrice":9504,"brand":"Xbox","genre":"Adventures","src":"https://via.placeholder.com/150x200"},{"name":"Product 91","price":10920,"finalPrice":9609.6,"brand":"Xbox","genre":"Shooter","src":"https://via.placeholder.com/150x200"},{"name":"Product 92","price":11040,"finalPrice":9715.2,"brand":"Nintendo","genre":"Sports","src":"https://via.placeholder.com/150x200"},{"name":"Product 93","price":11160,"finalPrice":9820.8,"brand":"Sony","genre":"Shooter","src":"https://via.placeholder.com/150x200"},{"name":"Product 94","price":11280,"finalPrice":9926.4,"brand":"Sony","genre":"Racing","src":"https://via.placeholder.com/150x200"},{"name":"Product 95","price":11400,"finalPrice":10032,"brand":"Xbox","genre":"Shooter","src":"https://via.placeholder.com/150x200"},{"name":"Product 96","price":11520,"finalPrice":10137.6,"brand":"Xbox","genre":"Party","src":"https://via.placeholder.com/150x200"},{"name":"Product 97","price":11640,"finalPrice":10243.2,"brand":"Xbox","genre":"Adventures","src":"https://via.placeholder.com/150x200"},{"name":"Product 98","price":11760,"finalPrice":10348.8,"brand":"Xbox","genre":"Racing","src":"https://via.placeholder.com/150x200"},{"name":"Product 99","price":11880,"finalPrice":10454.4,"brand":"Xbox","genre":"Sports","src":"https://via.placeholder.com/150x200"},{"name":"Product 100","price":12000,"finalPrice":10560,"brand":"Nintendo","genre":"Fighting","src":"https://via.placeholder.com/150x200"}]